python3d/__init__.py
python3d/particles.py
python3d/physic.py
python3d/sound.py
simple_python3d_engine-1.0.0.dist-info/licenses/LICENSE.txt
simple_python3d_engine-1.0.0.dist-info/METADATA
simple_python3d_engine-1.0.0.dist-info/WHEEL
simple_python3d_engine-1.0.0.dist-info/top_level.txt
simple_python3d_engine-1.0.0.dist-info/RECORD
