Metadata-Version: 2.4
Name: simple-python3d-engine
Version: 1.0.0
Author: remontmodema
License-File: LICENSE.txt
Requires-Dist: pygame
Dynamic: author
Dynamic: license-file
Dynamic: requires-dist
